tiptop/__about__.py
tiptop/__init__.py
tiptop/_app.py
tiptop/_battery.py
tiptop/_cpu.py
tiptop/_disk.py
tiptop/_helpers.py
tiptop/_info.py
tiptop/_mem.py
tiptop/_net.py
tiptop/_procs_list.py
tiptop/blockchar_stream.py
tiptop/braille_stream.py
tiptop-0.2.8.dist-info/LICENSE
tiptop-0.2.8.dist-info/METADATA
tiptop-0.2.8.dist-info/WHEEL
tiptop-0.2.8.dist-info/entry_points.txt
tiptop-0.2.8.dist-info/top_level.txt
tiptop-0.2.8.dist-info/RECORD
