Metadata-Version: 2.1
Name: tiptop
Version: 0.2.8
Summary: A better top
Author-email: Nico Schlömer <nico.schloemer@gmail.com>
License: The MIT License (MIT)
Project-URL: Code, https://github.com/nschloe/tiptop
Project-URL: Issues, https://github.com/nschloe/tiptop/issues
Project-URL: Funding, https://github.com/sponsors/nschloe
Classifier: Development Status :: 4 - Beta
Classifier: License :: OSI Approved :: MIT License
Classifier: Operating System :: POSIX :: Linux
Classifier: Operating System :: MacOS
Classifier: Programming Language :: Python
Classifier: Programming Language :: Python :: 3
Classifier: Programming Language :: Python :: 3.7
Classifier: Programming Language :: Python :: 3.8
Classifier: Programming Language :: Python :: 3.9
Classifier: Programming Language :: Python :: 3.10
Classifier: Topic :: Utilities
Requires-Python: >=3.7
License-File: LICENSE
Requires-Dist: py-cpuinfo
Requires-Dist: distro
Requires-Dist: psutil
Requires-Dist: rich (>=11.0.0)
Requires-Dist: textual (<0.2,>=0.1.15)
